phytominer/__init__.py
phytominer/api.py
phytominer/config.py
phytominer/data.py
phytominer/processing.py
phytominer/utils.py
phytominer/workflow.py
phytominer-0.2.0.dist-info/licenses/LICENSE
phytominer-0.2.0.dist-info/METADATA
phytominer-0.2.0.dist-info/WHEEL
phytominer-0.2.0.dist-info/top_level.txt
phytominer-0.2.0.dist-info/RECORD
