Metadata-Version: 2.4
Name: phytominer
Version: 0.2.0
Summary: A Python library for efficiently fetching and processing gene homolog data from the Phytozome database.
Author-email: Kris Kari <toffe.kari@gmail.com>
Project-URL: Homepage, https://github.com/boffus/PhytoMiner
Project-URL: Bug Tracker, https://github.com/boffus/PhytoMiner/issues
Classifier: License :: OSI Approved :: MIT License
Classifier: Operating System :: OS Independent
Classifier: Programming Language :: Python :: 3
Classifier: Programming Language :: Python :: 3.9
Classifier: Topic :: Scientific/Engineering :: Bio-Informatics
Requires-Python: >=3.9
License-File: LICENSE
Requires-Dist: pandas
Requires-Dist: intermine
Requires-Dist: requests
Requires-Dist: seaborn
Requires-Dist: matplotlib
Provides-Extra: dev
Requires-Dist: pytest; extra == "dev"
Requires-Dist: pytest-mock; extra == "dev"
Dynamic: license-file
